KGraber/KGraber.py
KGraber/__init__.py
KGraber-1.1.dist-info/DESCRIPTION.rst
KGraber-1.1.dist-info/METADATA
KGraber-1.1.dist-info/RECORD
KGraber-1.1.dist-info/WHEEL
KGraber-1.1.dist-info/entry_points.txt
KGraber-1.1.dist-info/metadata.json
KGraber-1.1.dist-info/top_level.txt
