Metadata-Version: 2.0
Name: KGraber
Version: 1.1
Summary: 这是一个用来从网页版全民K歌抓取用户自己作品并下载到本地的脚本
Home-page: https://github.com/wangzhizhou/KGraber
Author: 王志舟
Author-email: 824219521@qq.com
License: UNKNOWN
Platform: all
Classifier: Operating System :: OS Independent
Classifier: Programming Language :: Python
Requires-Dist: beautifulsoup4
Requires-Dist: requests
Requires-Dist: qrcode
Requires-Dist: pillow
